{
  "updatedAt": "2026-04-29T00:20:15.076Z",
  "absent": [
    {
      "tag": "#YVYCCQU08",
      "name": "Frenético",
      "townhallLevel": 18,
      "consecutiveAbsences": 4
    },
    {
      "tag": "#LJPQCQPYL",
      "name": "NOTJUN1OR",
      "townhallLevel": 18,
      "consecutiveAbsences": 3
    },
    {
      "tag": "#PPPUQPVJY",
      "name": "Rodrigo",
      "townhallLevel": 18,
      "consecutiveAbsences": 5
    },
    {
      "tag": "#QJLQLUURY",
      "name": "NenemPJL",
      "townhallLevel": 18,
      "consecutiveAbsences": 6
    },
    {
      "tag": "#L8RG2PV0G",
      "name": "joaoaoaoao",
      "townhallLevel": 18,
      "consecutiveAbsences": 1
    },
    {
      "tag": "#LV98Q8PYY",
      "name": "Vinicius",
      "townhallLevel": 18,
      "consecutiveAbsences": 4
    },
    {
      "tag": "#QQULJG9",
      "name": "david",
      "townhallLevel": 18,
      "consecutiveAbsences": 8
    },
    {
      "tag": "#8LL8J8UVG",
      "name": "NOT MOREIRA",
      "townhallLevel": 18,
      "consecutiveAbsences": 3
    },
    {
      "tag": "#JPVGQP8V",
      "name": "♤Pluto♤",
      "townhallLevel": 17,
      "consecutiveAbsences": 8
    },
    {
      "tag": "#LRC0U92LV",
      "name": "Dj_HenriqSP2",
      "townhallLevel": 18,
      "consecutiveAbsences": 1
    },
    {
      "tag": "#RC82GPG",
      "name": "tonton",
      "townhallLevel": 16,
      "consecutiveAbsences": 8
    },
    {
      "tag": "#LR2U2PRP2",
      "name": "NARNIA",
      "townhallLevel": 16,
      "consecutiveAbsences": 8
    },
    {
      "tag": "#GRVUL9PPR",
      "name": "Nenem",
      "townhallLevel": 17,
      "consecutiveAbsences": 7
    },
    {
      "tag": "#GU2PP98GU",
      "name": "NenemRaid l",
      "townhallLevel": 9,
      "consecutiveAbsences": 8
    },
    {
      "tag": "#GVRVR82YU",
      "name": "NenemRaid",
      "townhallLevel": 9,
      "consecutiveAbsences": 8
    }
  ]
}